[
    {
        "source": "Коркина, Евдокия Иннокентьевна. Наклонения глагола в якутском языке / Е. И. Коркина ; Акад. наук СССР, Якут. фил. Сиб. отд- ния, Ин-т яз., лит. и истории ; [отв. ред. проф. Л. Н. Харитонов]. - Москва : Наука, 1970. - 306 с.",
        "page": 50,
        "chapter": "Глава I. Настояще-будущее время",
        "topic": "Значение настояще-будущего времени в якутском языке",
        "section": 9,
        "notes": "Отрицательная форма настояще-будущего времени может быть использована в качестве одного из средств выражения оттенка пожелания, просьбы к совершению какого-либо действия или, наоборот, осуждения по поводу уже состоявшегося действия.",
        "sah": "Оннукка мин да түбэһэн аһаабаппын!",
        "ru": "Что бы и мне угодить в такое и наесться вдоволь (оттенок пожелания)!",
        "id": 1,
        "parses": [
           {"pos": 1, "text": "Оннукка", "type": "title", "fst": "fst", "root": "ол", "affixes": ["+Pron", "+DEF", "+DAT"]},
           {"pos": 2, "text": "мин", "type": "lowercase", "fst": "fst", "root": "мин", "affixes": ["+Pron"]},
           {"pos": 3, "text": "да", "type": "lowercase", "fst": "fst", "root": "да", "affixes": ["+Part"]},
           {"pos": 4, "text": "түбэһэн", "type": "lowercase", "fst": "fst", "root": "түбэс", "affixes": ["+V", "+CONV#1"]},
           {"pos": 5, "text": "аһаабаппын", "type": "lowercase", "fst": "fst", "root": "ас", "affixes": ["+N", "+VRBLZ#3", "+NEG", "+PART_PRES", "+1SG"]},
           {"pos": 6, "text": "!", "type": "exclamation", "fst": "fst"}
        ]
    },    
    {
        "source": "Коркина, Евдокия Иннокентьевна. Наклонения глагола в якутском языке / Е. И. Коркина ; Акад. наук СССР, Якут. фил. Сиб. отд- ния, Ин-т яз., лит. и истории ; [отв. ред. проф. Л. Н. Харитонов]. - Москва : Наука, 1970. - 306 с.",
        "page": 50,
        "chapter": "Глава I. Настояще-будущее время",
        "topic": "Значение настояще-будущего времени в якутском языке",
        "section": 9,
        "notes": "Отрицательная форма настояще-будущего времени может быть использована в качестве одного из средств выражения оттенка пожелания, просьбы к совершению какого-либо действия или, наоборот, осуждения по поводу уже состоявшегося действия.",
        "sah": "Саҥата да суох олорбоккун.",
        "ru": "Сидела бы молчком (оттенок осуждения).",
        "id": 4,
        "parses": [
           {"pos": 1, "text": "Саҥата", "type": "title", "fst": "fst", "root": "саҥа", "affixes": ["+N", "+POSS.3SG"]},
           {"pos": 2, "text": "да", "type": "lowercase", "fst": "fst", "root": "да", "affixes": ["+Part"]},
           {"pos": 3, "text": "суох", "type": "lowercase", "fst": "fst", "root": "суох", "affixes": ["+N"]},
           {"pos": 4, "text": "олорбоккун", "type": "lowercase", "fst": "fst", "root": "олор", "affixes": ["+V", "+NEG", "+PART_PRES", "+2SG"]},
           {"pos": 5, "text": ".", "type": "period", "fst": "fst"}
        ]
    },
    {
        "source": "Коркина, Евдокия Иннокентьевна. Наклонения глагола в якутском языке / Е. И. Коркина ; Акад. наук СССР, Якут. фил. Сиб. отд- ния, Ин-т яз., лит. и истории ; [отв. ред. проф. Л. Н. Харитонов]. - Москва : Наука, 1970. - 306 с.",
        "page": 51,
        "chapter": "Глава I. Настояще-будущее время",
        "topic": "Значение настояще-будущего времени в якутском языке",
        "section": 9,
        "notes": "В таком употреблении данная форма довольно часто может присоединять к себе некоторые модальные, эмоционально-усилительные частицы (ээ, эбээт, даҕаны), которые еще более усиливают вышеуказанные оттенки пожелания, просьбы и наряду с ними дополнительно передают оттенки легкого совета, призыва или досады, сожаления по поводу уже совершенного действия.",
        "sah": "Гражданка, бу хаһыаты эн миэхэ атыылаабаккын ээ!",
        "ru": "Не продадите ли вы, гражданка, эту газету мне!",
        "id": 5,
        "parses": [
           {"pos": 1, "text": "Гражданка", "type": "title", "fst": "fst", "root": "гражданка", "affixes": ["+N"]},
           {"pos": 2, "text": ",", "type": "comma", "fst": "fst"},
           {"pos": 3, "text": "бу", "type": "lowercase", "fst": "fst", "root": "бу", "affixes": ["+Pron"]},
           {"pos": 4, "text": "хаһыаты", "type": "lowercase", "fst": "fst", "root": "хаһыат", "affixes": ["+N", "+ACC"]},
           {"pos": 5, "text": "эн", "type": "lowercase", "fst": "fst", "root": "эн", "affixes": ["+Pron"]},
           {"pos": 6, "text": "миэхэ", "type": "lowercase", "fst": "fst", "root": "мин", "affixes": ["+Pron", "+DAT"]},
           {"pos": 7, "text": "атыылаабаккын", "type": "lowercase", "fst": "fst", "root": "атыы", "affixes": ["+N", "+VRBLZ#1", "+NEG", "+PART_PRES", "+2SG"]},
           {"pos": 8, "text": "ээ", "type": "lowercase", "fst": "fst", "root": "ээ", "affixes": ["+Part"]},
           {"pos": 9, "text": "!", "type": "exclamation", "fst": "fst"}
        ]
    },
    {
        "source": "Коркина, Евдокия Иннокентьевна. Наклонения глагола в якутском языке / Е. И. Коркина ; Акад. наук СССР, Якут. фил. Сиб. отд- ния, Ин-т яз., лит. и истории ; [отв. ред. проф. Л. Н. Харитонов]. - Москва : Наука, 1970. - 306 с.",
        "page": 51,
        "chapter": "Глава I. Настояще-будущее время",
        "topic": "Значение настояще-будущего времени в якутском языке",
        "section": 9,
        "notes": "В таком употреблении данная форма довольно часто может присоединять к себе некоторые модальные, эмоционально-усилительные частицы (ээ, эбээт, да5аны), которые еще более усиливают вышеуказанные оттенки пожелания, просьбы и наряду с ними дополнительно передают оттенки легкого совета, призыва или досады, сожаления по поводу уже совершенного действия.",
        "sah": "Кыратык үҥкүүлүү түспэппит ээ?",
        "ru": "Не потанцевать ли нам немного?",
        "id": 6,
        "parses": [
           {"pos": 1, "text": "Кыратык", "type": "title", "fst": "fst", "root": "кыра", "affixes": ["+Adj", "+ADVZ#5"]},
           {"pos": 2, "text": "үҥкүүлүү", "type": "lowercase", "fst": "fst", "root": "үҥкүү", "affixes": ["+N", "+VRBLZ#1", "+CONV#2"]},
           {"pos": 3, "text": "түспэппит", "type": "lowercase", "fst": "fst", "root": "түс", "affixes": ["+V", "+NEG", "+PART_PRES", "+1PL"]},
           {"pos": 4, "text": "ээ", "type": "lowercase", "fst": "fst", "root": "ээ", "affixes": ["+Part"]},
           {"pos": 5, "text": "?", "type": "question", "fst": "fst"}
        ]
    },
    {
        "source": "Коркина, Евдокия Иннокентьевна. Наклонения глагола в якутском языке / Е. И. Коркина ; Акад. наук СССР, Якут. фил. Сиб. отд- ния, Ин-т яз., лит. и истории ; [отв. ред. проф. Л. Н. Харитонов]. - Москва : Наука, 1970. - 306 с.",
        "page": 51,
        "chapter": "Глава I. Настояще-будущее время",
        "topic": "Значение настояще-будущего времени в якутском языке",
        "section": 9,
        "notes": "В таком употреблении данная форма довольно часто может присоединять к себе некоторые модальные, эмоционально-усилительные частицы (ээ, эбээт, да5аны), которые еще более усиливают вышеуказанные оттенки пожелания, просьбы и наряду с ними дополнительно передают оттенки легкого совета, призыва или досады, сожаления по поводу уже совершенного действия.",
        "sah": "Дэриэбинэттэн баран хаал диэн эн киниэхэ сүбэлээбэккин эбээт.",
        "ru": "Ты бы посоветовал (не посоветуешь ли), чтобы он совсем уехал из деревни.",
        "id": 7,
        "parses": [
           {"pos": 1, "text": "Дэриэбинэттэн", "type": "title", "fst": "fst", "root": "дэриэбинэ", "affixes": ["+N", "+ABL"]},
           {"pos": 2, "text": "баран", "type": "lowercase", "fst": "fst", "root": "бар", "affixes": ["+V", "+CONV#1"]},
           {"pos": 3, "text": "хаал", "type": "lowercase", "fst": "fst", "root": "хаал", "affixes": ["+V"]},
           {"pos": 4, "text": "диэн", "type": "lowercase", "fst": "fst", "root": "диэ", "affixes": ["+V", "+CONV#1"]},
           {"pos": 5, "text": "эн", "type": "lowercase", "fst": "fst", "root": "эн", "affixes": ["+Pron"]},
           {"pos": 6, "text": "киниэхэ", "type": "lowercase", "fst": "fst", "root": "кини", "affixes": ["+Pron", "+DAT"]},
           {"pos": 7, "text": "сүбэлээбэккин", "type": "lowercase", "fst": "fst", "root": "сүбэ", "affixes": ["+N", "+VRBLZ#1", "+NEG", "+PART_PRES", "+2SG"]},
           {"pos": 8, "text": "эбээт", "type": "lowercase", "fst": "fst", "root": "эбээт", "affixes": ["+Part"]},
           {"pos": 9, "text": ".", "type": "period", "fst": "fst"}
        ]
    },
    {
        "source": "Коркина, Евдокия Иннокентьевна. Наклонения глагола в якутском языке / Е. И. Коркина ; Акад. наук СССР, Якут. фил. Сиб. отд- ния, Ин-т яз., лит. и истории ; [отв. ред. проф. Л. Н. Харитонов]. - Москва : Наука, 1970. - 306 с.",
        "page": 51,
        "chapter": "Глава I. Настояще-будущее время",
        "topic": "Значение настояще-будущего времени в якутском языке",
        "section": 9,
        "notes": "В таком употреблении данная форма довольно часто может присоединять к себе некоторые модальные, эмоционально-усилительные частицы (ээ, эбээт, да5аны), которые еще более усиливают вышеуказанные оттенки пожелания, просьбы и наряду с ними дополнительно передают оттенки легкого совета, призыва или досады, сожаления по поводу уже совершенного действия.",
        "sah": "Оо, биһигини эрдэ уһугуннарбаккын даҕаны!",
        "ru": "Хоть бы ты разбудила нас пораньше!",
        "id": 9,
        "parses": [
           {"pos": 1, "text": "Оо", "type": "title", "fst": "fst", "root": "оо", "affixes": ["+INJ"]},
           {"pos": 2, "text": ",", "type": "comma", "fst": "fst"},
           {"pos": 3, "text": "биһигини", "type": "lowercase", "fst": "fst", "root": "биһиги", "affixes": ["+Pron", "+ACC"]},
           {"pos": 4, "text": "эрдэ", "type": "lowercase", "fst": "fst", "root": "эрдэ", "affixes": ["+Adv"]},
           {"pos": 5, "text": "уһугуннарбаккын", "type": "lowercase", "fst": "fst", "root": "уһугун", "affixes": ["+V", "+CSTV", "+NEG", "+PART_PRES", "+2SG"]},
           {"pos": 6, "text": "даҕаны", "type": "lowercase", "fst": "fst", "root": "даҕаны", "affixes": ["+Part"]},
           {"pos": 7, "text": "!", "type": "exclamation", "fst": "fst"}
        ]
    },
    {
        "source": "Коркина, Евдокия Иннокентьевна. Наклонения глагола в якутском языке / Е. И. Коркина ; Акад. наук СССР, Якут. фил. Сиб. отд- ния, Ин-т яз., лит. и истории ; [отв. ред. проф. Л. Н. Харитонов]. - Москва : Наука, 1970. - 306 с.",
        "page": 51,
        "chapter": "Глава I. Настояще-будущее время",
        "topic": "Значение настояще-будущего времени в якутском языке",
        "section": 9,
        "notes": "Этот же оттенок пожелания, просьбы к совершению действия и сожаления по поводу уже совершенного действия несет отрицательная форма инфинитива от причастия на -ар. В данном случае указанные оттенки передаются в безличной форме.",
        "sah": "Колхозка киирэн хаалбакка.",
        "ru": "Надо бы в колхоз вступить.",
        "id": 10,
        "parses": [
           {"pos": 1, "text": "Колхозка", "type": "title", "fst": "fst", "root": "колхоз", "affixes": ["+N", "+DAT"]},
           {"pos": 2, "text": "киирэн", "type": "lowercase", "fst": "fst", "root": "киир", "affixes": ["+V", "+CONV#1"]},
           {"pos": 3, "text": "хаалбакка", "type": "lowercase", "fst": "fst", "root": "хаал", "affixes": ["+V", "+NEG", "+PART_PRES", "+DAT"]},
           {"pos": 4, "text": ".", "type": "period", "fst": "fst"}
        ]
    },
    {
        "source": "Коркина, Евдокия Иннокентьевна. Наклонения глагола в якутском языке / Е. И. Коркина ; Акад. наук СССР, Якут. фил. Сиб. отд- ния, Ин-т яз., лит. и истории ; [отв. ред. проф. Л. Н. Харитонов]. - Москва : Наука, 1970. - 306 с.",
        "page": 51,
        "chapter": "Глава I. Настояще-будущее время",
        "topic": "Значение настояще-будущего времени в якутском языке",
        "section": 9,
        "notes": "Этот же оттенок пожелания, просьбы к совершению действия и сожаления по поводу уже совершенного действия несет отрицательная форма инфинитива от причастия на -ар. В данном случае указанные оттенки передаются в безличной форме.",
        "sah": "Тыый, мас киллэрэн, уот отто охсубакка.",
        "ru": "Тьфу, ведь давно бы следовало занести дрова и сразу затопить печь.",
        "id": 12,
        "parses": [
           {"pos": 1, "text": "Тыый", "type": "title", "fst": "fst", "root": "тыый", "affixes": ["+INJ"]},
           {"pos": 2, "text": ",", "type": "comma", "fst": "fst"},
           {"pos": 3, "text": "мас", "type": "lowercase", "fst": "fst", "root": "мас", "affixes": ["+N"]},
           {"pos": 4, "text": "киллэрэн", "type": "lowercase", "fst": "fst", "root": "киллэр", "affixes": ["+V", "+CONV#1"]},
           {"pos": 5, "text": ",", "type": "comma", "fst": "fst"},
           {"pos": 6, "text": "уот", "type": "lowercase", "fst": "fst", "root": "уот", "affixes": ["+N"]},
           {"pos": 7, "text": "отто", "type": "lowercase", "fst": "fst", "root": "отун", "affixes": ["+V", "+CONV#2"]},
           {"pos": 8, "text": "охсубакка", "type": "lowercase", "fst": "fst", "root": "оҕус", "affixes": ["+V", "+NEG", "+PART_PRES", "+DAT"]},
           {"pos": 9, "text": ".", "type": "period", "fst": "fst"}
        ]
    }
]