[
   {
      "source": "Грамматика современного якутского литературного языка : [в 2 томах] / Акад. наук СССР, Сиб. отд- ние, Якут. фил., Ин-т яз. лит.и истории; [редкол.: Е. И. Убрятова (отв. ред.), Е. И. Коркина, Л. Н. Харитонов, Н. Е. Петров]. - Москва : Наука, 1982-1995. Т. 1: Фонетика и морфология / [Л. Н. Харитонов, Н. Д. Дьячковский, С. А. Иванов и др.]. - Москва: Наука, 1982. - 495 с.",
      "page": 358,
      "chapter": "Наречие",
      "topic": "Синтаксические функции и связи наречий. Сочетание наречий с глагольными",
      "section": 718,
      "notes": "Имя действия на -ыы. Здесь примыкающие к имени определения и обстоятельства, переведенные в форме русских прилагательных, в якутском языке являются наречиями. Само собою разумеется, что данное имя действия вместе с примыкающим к нему наречием может иметь любые формы изменения и входить в состав различных синтаксических построений, свойственных именам.",
      "sah": "түргэнник хаамыы",
      "ru": "быстрая ходьба",
      "id": 1,
      "parses": [
         {"pos": 1, "text": "түргэнник", "type": "lowercase", "fst": "fst", "root": "түргэн", "affixes": ["+Adj", "+ADVZ#5"]},
         {"pos": 2, "text": "хаамыы", "type": "lowercase", "fst": "fst", "root": "хаамп", "affixes": ["+V", "+NMLZ#2"]}
      ]
   },
   {
      "source": "Грамматика современного якутского литературного языка : [в 2 томах] / Акад. наук СССР, Сиб. отд- ние, Якут. фил., Ин-т яз. лит.и истории; [редкол.: Е. И. Убрятова (отв. ред.), Е. И. Коркина, Л. Н. Харитонов, Н. Е. Петров]. - Москва : Наука, 1982-1995. Т. 1: Фонетика и морфология / [Л. Н. Харитонов, Н. Д. Дьячковский, С. А. Иванов и др.]. - Москва: Наука, 1982. - 495 с.",
      "page": 358,
      "chapter": "Наречие",
      "topic": "Синтаксические функции и связи наречий. Сочетание наречий с глагольными",
      "section": 718,
      "notes": "Имя действия на -ыы. Здесь примыкающие к имени определения и обстоятельства, переведенные в форме русских прилагательных, в якутском языке являются наречиями. Само собою разумеется, что данное имя действия вместе с примыкающим к нему наречием может иметь любые формы изменения и входить в состав различных синтаксических построений, свойственных именам.",
      "sah": "сатыы сырыы",
      "ru": "хождение пешком",
      "id": 2,
      "parses": [
         {"pos": 1, "text": "сатыы", "type": "lowercase", "fst": "fst", "root": "сатаа", "affixes": ["+V", "+CONV#2"]},
         {"pos": 1, "text": "сатыы", "type": "lowercase", "fst": "fst", "root": "сатыы", "affixes": ["+Adv"]},
         {"pos": 1, "text": "сатыы", "type": "lowercase", "fst": "fst", "root": "сай", "affixes": ["+V", "+CSTV", "+NMLZ#2"]},
         {"pos": 1, "text": "сатыы", "type": "lowercase", "fst": "fst", "root": "сай", "affixes": ["+V", "+CSTV", "+CONV#2"]},
         {"pos": 2, "text": "сырыы", "type": "lowercase", "fst": "fst", "root": "сырыы", "affixes": ["+N"]}
      ]
   },
   {
      "source": "Грамматика современного якутского литературного языка : [в 2 томах] / Акад. наук СССР, Сиб. отд- ние, Якут. фил., Ин-т яз. лит.и истории; [редкол.: Е. И. Убрятова (отв. ред.), Е. И. Коркина, Л. Н. Харитонов, Н. Е. Петров]. - Москва : Наука, 1982-1995. Т. 1: Фонетика и морфология / [Л. Н. Харитонов, Н. Д. Дьячковский, С. А. Иванов и др.]. - Москва: Наука, 1982. - 495 с.",
      "page": 359,
      "chapter": "Наречие",
      "topic": "Синтаксические функции и связи наречий. Сочетание наречий с глагольными",
      "section": 718,
      "notes": "Имя действия на -ыы. Здесь примыкающие к имени определения и обстоятельства, переведенные в форме русских прилагательных, в якутском языке являются наречиями. Само собою разумеется, что данное имя действия вместе с примыкающим к нему наречием может иметь любые формы изменения и входить в состав различных синтаксических построений, свойственных именам.",
      "sah": "үлэ саҥардыы тэриллиитэ",
      "ru": "первоначальная организация работы",
      "id": 3,
      "parses": [
         {"pos": 1, "text": "үлэ", "type": "lowercase", "fst": "fst", "root": "үлэ", "affixes": ["+N"]},
         {"pos": 2, "text": "саҥардыы", "type": "lowercase", "fst": "fst", "root": "саҥардыы", "affixes": ["+Adv"]},
         {"pos": 2, "text": "саҥардыы", "type": "lowercase", "fst": "fst", "root": "саҥа", "affixes": ["+Adj", "+VRBLZ#4", "+ITER#2", "+NMLZ#2"]},
         {"pos": 2, "text": "саҥардыы", "type": "lowercase", "fst": "fst", "root": "саҥа", "affixes": ["+Adj", "+VRBLZ#4", "+ITER#2", "+CONV#2"]},
         {"pos": 2, "text": "саҥардыы", "type": "lowercase", "fst": "fst", "root": "саҥа", "affixes": ["+Adj", "+VRBLZ#4", "+CSTV", "+NMLZ#2"]},
         {"pos": 2, "text": "саҥардыы", "type": "lowercase", "fst": "fst", "root": "саҥа", "affixes": ["+Adj", "+VRBLZ#4", "+CSTV", "+CONV#2"]},
         {"pos": 2, "text": "саҥардыы", "type": "lowercase", "fst": "fst", "root": "саҥа", "affixes": ["+N", "+VRBLZ#4", "+ITER#2", "+NMLZ#2"]},
         {"pos": 2, "text": "саҥардыы", "type": "lowercase", "fst": "fst", "root": "саҥа", "affixes": ["+N", "+VRBLZ#4", "+ITER#2", "+CONV#2"]},
         {"pos": 2, "text": "саҥардыы", "type": "lowercase", "fst": "fst", "root": "саҥа", "affixes": ["+N", "+VRBLZ#4", "+CSTV", "+NMLZ#2"]},
         {"pos": 2, "text": "саҥардыы", "type": "lowercase", "fst": "fst", "root": "саҥа", "affixes": ["+N", "+VRBLZ#4", "+CSTV", "+CONV#2"]},
         {"pos": 3, "text": "тэриллиитэ", "type": "lowercase", "fst": "fst", "root": "тэрил", "affixes": ["+N", "+ADVZ#6", "+POSS.3SG"]},
         {"pos": 3, "text": "тэриллиитэ", "type": "lowercase", "fst": "fst", "root": "тэрил", "affixes": ["+N", "+VRBLZ#1", "+NMLZ#2", "+POSS.3SG"]},
         {"pos": 3, "text": "тэриллиитэ", "type": "lowercase", "fst": "fst", "root": "тэрил", "affixes": ["+N", "+VRBLZ#1", "+NMLZ#2", "+PRTV"]},
         {"pos": 3, "text": "тэриллиитэ", "type": "lowercase", "fst": "fst", "root": "тэрил", "affixes": ["+N", "+VRBLZ#1", "+CONV#2", "+ADVZ#8"]},
         {"pos": 3, "text": "тэриллиитэ", "type": "lowercase", "fst": "fst", "root": "тэрий", "affixes": ["+V", "+PASS", "+NMLZ#2", "+POSS.3SG"]},
         {"pos": 3, "text": "тэриллиитэ", "type": "lowercase", "fst": "fst", "root": "тэрий", "affixes": ["+V", "+PASS", "+NMLZ#2", "+PRTV"]},
         {"pos": 3, "text": "тэриллиитэ", "type": "lowercase", "fst": "fst", "root": "тэрий", "affixes": ["+V", "+PASS", "+CONV#2", "+ADVZ#8"]},
         {"pos": 3, "text": "тэриллиитэ", "type": "lowercase", "fst": "fst", "root": "тиэр", "affixes": ["+V", "+PASS", "+NMLZ#2", "+POSS.3SG"]},
         {"pos": 3, "text": "тэриллиитэ", "type": "lowercase", "fst": "fst", "root": "тиэр", "affixes": ["+V", "+PASS", "+NMLZ#2", "+PRTV"]},
         {"pos": 3, "text": "тэриллиитэ", "type": "lowercase", "fst": "fst", "root": "тиэр", "affixes": ["+V", "+PASS", "+CONV#2", "+ADVZ#8"]}
      ]
   }
]