[
   {
      "source": "Петров, Николай Егорович. Модальные слова в якутском языке / Н. Е. Петров ; ответственный редактор Е. И. Коркина ; Академия наук СССР, Сибирское отделение, Якутский филиал, Институт языка, литературы и истории. - Новосибирск : Наука, 1984. - 204 с.",
      "page": 149,
      "chapter": "Глава III Функционально-модальные слова",
      "topic": "1. Именные модальные слова: 10. Куолутунан.",
      "section": 10,
      "notes": "Имя куолу 'обычай, обыкновение, закон' в форме орудного падежа притяжательного склонения грамматикализируется и выступает как модальное слово, выражающее мнение говорящего, что высказываемое действие он считает обычным, привычным, постоянно присущим упоминаемому субъекту.",
      "sah": "Быладыыымарал этиитэ, куолутунан, кыайан сааһыламмата.",
      "ru": "Выступление Владимирова, как всегда, было туманным.",
      "id": 1,
      "parses": [
         {"pos": 1, "text": "Быладыыымарал", "type": "title", "fst": "fst"},
         {"pos": 2, "text": "этиитэ", "type": "lowercase", "fst": "fst", "root": "эт", "affixes": ["+N", "+VRBLZ#3", "+NMLZ#2", "+POSS.3SG"]},
         {"pos": 2, "text": "этиитэ", "type": "lowercase", "fst": "fst", "root": "эт", "affixes": ["+N", "+VRBLZ#3", "+NMLZ#2", "+PRTV"]},
         {"pos": 2, "text": "этиитэ", "type": "lowercase", "fst": "fst", "root": "эт", "affixes": ["+N", "+VRBLZ#3", "+CONV#2", "+ADVZ#8"]},
         {"pos": 2, "text": "этиитэ", "type": "lowercase", "fst": "fst", "root": "эт", "affixes": ["+V", "+NMLZ#2", "+POSS.3SG"]},
         {"pos": 2, "text": "этиитэ", "type": "lowercase", "fst": "fst", "root": "эт", "affixes": ["+V", "+NMLZ#2", "+PRTV"]},
         {"pos": 3, "text": ",", "type": "comma", "fst": "fst"},
         {"pos": 4, "text": "куолутунан", "type": "lowercase", "fst": "fst", "root": "куолу", "affixes": ["+N", "+VRBLZ#2", "+CSTV", "+ADVZ#1", "+INST"]},
         {"pos": 4, "text": "куолутунан", "type": "lowercase", "fst": "fst", "root": "куолу", "affixes": ["+N", "+VRBLZ#2", "+CSTV", "+REFL", "+CONV#1"]},
         {"pos": 4, "text": "куолутунан", "type": "lowercase", "fst": "fst", "root": "куолу", "affixes": ["+N", "+POSS.3SG", "+INST"]},
         {"pos": 5, "text": ",", "type": "comma", "fst": "fst"},
         {"pos": 6, "text": "кыайан", "type": "lowercase", "fst": "fst", "root": "кыай", "affixes": ["+V", "+CONV#1"]},
         {"pos": 6, "text": "кыайан", "type": "lowercase", "fst": "fst", "root": "кыа", "affixes": ["+N", "+VRBLZ#2", "+CONV#1"]},
         {"pos": 7, "text": "сааһыламмата", "type": "lowercase", "fst": "fst"},
         {"pos": 8, "text": ".", "type": "period", "fst": "fst"}
      ]
   },
   {
      "source": "Петров, Николай Егорович. Модальные слова в якутском языке / Н. Е. Петров ; ответственный редактор Е. И. Коркина ; Академия наук СССР, Сибирское отделение, Якутский филиал, Институт языка, литературы и истории. - Новосибирск : Наука, 1984. - 204 с.",
      "page": 149,
      "chapter": "Глава III Функционально-модальные слова",
      "topic": "1. Именные модальные слова: 10. Куолутунан.",
      "section": 10,
      "notes": "Имя куолу 'обычай, обыкновение, закон' в форме орудного падежа притяжательного склонения грамматикализируется и выступает как модальное слово, выражающее мнение говорящего, что высказываемое действие он считает обычным, привычным, постоянно присущим упоминаемому субъекту.",
      "sah": "Аня, куолутунан, улаханнык күллэ.",
      "ru": "Аня, по обыкновению, громко рассмеялась.",
      "id": 2,
      "parses": [
         {"pos": 1, "text": "Аня", "type": "title", "fst": "fst"},
         {"pos": 2, "text": ",", "type": "comma", "fst": "fst"},
         {"pos": 3, "text": "куолутунан", "type": "lowercase", "fst": "fst", "root": "куолу", "affixes": ["+N", "+VRBLZ#2", "+CSTV", "+ADVZ#1", "+INST"]},
         {"pos": 3, "text": "куолутунан", "type": "lowercase", "fst": "fst", "root": "куолу", "affixes": ["+N", "+VRBLZ#2", "+CSTV", "+REFL", "+CONV#1"]},
         {"pos": 3, "text": "куолутунан", "type": "lowercase", "fst": "fst", "root": "куолу", "affixes": ["+N", "+POSS.3SG", "+INST"]},
         {"pos": 4, "text": ",", "type": "comma", "fst": "fst"},
         {"pos": 5, "text": "улаханнык", "type": "lowercase", "fst": "fst", "root": "улахан", "affixes": ["+Adj", "+ADVZ#5"]},
         {"pos": 6, "text": "күллэ", "type": "lowercase", "fst": "fst", "root": "күл", "affixes": ["+N", "+PRTV"]},
         {"pos": 6, "text": "күллэ", "type": "lowercase", "fst": "fst", "root": "күл", "affixes": ["+V", "+PST.3SG"]},
         {"pos": 7, "text": ".", "type": "period", "fst": "fst"}
      ]
   },
   {
      "source": "Петров, Николай Егорович. Модальные слова в якутском языке / Н. Е. Петров ; ответственный редактор Е. И. Коркина ; Академия наук СССР, Сибирское отделение, Якутский филиал, Институт языка, литературы и истории. - Новосибирск : Наука, 1984. - 204 с.",
      "page": 149,
      "chapter": "Глава III Функционально-модальные слова",
      "topic": "1. Именные модальные слова: 10. Куолутунан.",
      "section": 10,
      "notes": "Модальное слово куолутунан имеет синонимы идэтинэн (от идэ 'обычай, привычка'), үгэһинэн (от үгэс 'привычка'), которые по своему значению полностью соответствуют ему и отличаются от куолутунан лишь менее активным употреблением.",
      "sah": "Эдэр дьахтар, үгэһинэн, халҕаны тиэрэ тарпакка арыычча кыбыллан киирэр.",
      "ru": "Молодая женщина, по привычке, дверь не открывает наотмашь, а заходит в дом протискиваясь.",
      "id": 10,
      "parses": [
         {"pos": 1, "text": "Эдэр", "type": "title", "fst": "fst", "root": "эдэр", "affixes": ["+Adj"]},
         {"pos": 2, "text": "дьахтар", "type": "lowercase", "fst": "fst", "root": "дьахтар", "affixes": ["+N"]},
         {"pos": 3, "text": ",", "type": "comma", "fst": "fst"},
         {"pos": 4, "text": "үгэһинэн", "type": "lowercase", "fst": "fst", "root": "үгэс", "affixes": ["+N", "+INST"]},
         {"pos": 4, "text": "үгэһинэн", "type": "lowercase", "fst": "fst", "root": "үгэс", "affixes": ["+N", "+POSS.3SG", "+INST"]},
         {"pos": 5, "text": ",", "type": "comma", "fst": "fst"},
         {"pos": 6, "text": "халҕаны", "type": "lowercase", "fst": "fst", "root": "халҕан", "affixes": ["+N", "+ACC"]},
         {"pos": 7, "text": "тиэрэ", "type": "lowercase", "fst": "fst", "root": "тиэр", "affixes": ["+V", "+CONV#2"]},
         {"pos": 8, "text": "тарпакка", "type": "lowercase", "fst": "fst"},
         {"pos": 9, "text": "арыычча", "type": "lowercase", "fst": "fst", "root": "арыычча", "affixes": ["+Adv"]},
         {"pos": 10, "text": "кыбыллан", "type": "lowercase", "fst": "fst", "root": "кып", "affixes": ["+V", "+PASS", "+CONV#1"]},
         {"pos": 10, "text": "кыбыллан", "type": "lowercase", "fst": "fst", "root": "кый", "affixes": ["+V", "+NMLZ#4", "+VRBLZ#1", "+REFL"]},
         {"pos": 11, "text": "киирэр", "type": "lowercase", "fst": "fst", "root": "киир", "affixes": ["+V", "+PART_PRES"]},
         {"pos": 12, "text": ".", "type": "period", "fst": "fst"}
      ]
   }
]