[
   {
      "source": "Коркина, Евдокия Иннокентьевна. Деепричастия в якутском языке / Е. И. Коркина; отв. ред. к. филол. н. Н. Е. Петров; Акад. наук СССР, Сиб. отд-ние, Якут. фил., Ин-т яз., лит. и истории. - Новосибирск : Наука, Сибирское отделение, 1985. - 203 с.",
      "page": 32,
      "chapter": "Глава I. Морфологическое описание деепричастий якутского языка",
      "topic": "Первичные деепричастия. 2. Деепричастие на -а/-ын",
      "section": 23,
      "notes": "Деепричастия на -а/-ны в якутском языке могут употребляться и в парном виде, т.е. могут сочетаться деепричастные формы от основ разных глаголов. Чаще сочетаются основы, близкие по своему значению, которыми выражается единое понятие.",
      "sah": "Үөлээннээх дьон үөрэ-көтө көрүстүлэр.",
      "ru": "Друзья встретились веселясь-радуясь.",
      "id": 1,
      "parses": [
         {"pos": 1, "text": "Үөлээннээх", "type": "title", "fst": "ymv", "root": "үөлээн", "affixes": ["+N", "+ADJZ#1"]},
         {"pos": 2, "text": "дьон", "type": "lowercase", "fst": "ymv", "root": "дьон", "affixes": ["+N"]},
         {"pos": 3, "text": "үөрэ", "type": "lowercase", "fst": "ymv", "root": "үөр", "affixes": ["+V", "+CONV#2"]},
         {"pos": 4, "text": "-", "type": "hyphen", "fst": "ymv"},
         {"pos": 5, "text": "көтө", "type": "lowercase", "fst": "ymv", "root": "көт", "affixes": ["+V", "+CONV#2"]},
         {"pos": 6, "text": "көрүстүлэр", "type": "lowercase", "fst": "ymv", "root": "көр", "affixes": ["+V", "+RECP", "+PST.3PL"]},
         {"pos": 7, "text": ".", "type": "period", "fst": "ymv"}
      ]
   },
   {
      "source": "Коркина, Евдокия Иннокентьевна. Деепричастия в якутском языке / Е. И. Коркина; отв. ред. к. филол. н. Н. Е. Петров; Акад. наук СССР, Сиб. отд-ние, Якут. фил., Ин-т яз., лит. и истории. - Новосибирск : Наука, Сибирское отделение, 1985. - 203 с.",
      "page": 32,
      "chapter": "Глава I. Морфологическое описание деепричастий якутского языка",
      "topic": "Первичные деепричастия. 2. Деепричастие на -а/-ын",
      "section": 23,
      "notes": "Деепричастия на -а/-ны в якутском языке могут употребляться и в парном виде, т.е. могут сочетаться деепричастные формы от основ разных глаголов. Чаще сочетаются основы, близкие по своему значению, которыми выражается единое понятие.",
      "sah": "Улаханнык сөбүлүү-үөрэ иһиттэ.",
      "ru": "(Он) воспринял весьма удовлетворенно-радостно.",
      "id": 2,
      "parses": [
         {"pos": 1, "text": "Улаханнык", "type": "title", "fst": "ymv", "root": "улахан", "affixes": ["+Adj", "+ADVZ#5"]},
         {"pos": 2, "text": "сөбүлүү", "type": "lowercase", "fst": "ymv", "root": "сөбүлээ", "affixes": ["+V", "+CONV#2"]},
         {"pos": 3, "text": "-", "type": "hyphen", "fst": "ymv"},
         {"pos": 4, "text": "үөрэ", "type": "lowercase", "fst": "ymv", "root": "үөр", "affixes": ["+V", "+CONV#2"]},
         {"pos": 5, "text": "иһиттэ", "type": "lowercase", "fst": "ymv", "root": "иһит", "affixes": ["+V", "+PST.3SG"]},
         {"pos": 6, "text": ".", "type": "period", "fst": "ymv"}
      ]
   },
   {
      "source": "Коркина, Евдокия Иннокентьевна. Деепричастия в якутском языке / Е. И. Коркина; отв. ред. к. филол. н. Н. Е. Петров; Акад. наук СССР, Сиб. отд-ние, Якут. фил., Ин-т яз., лит. и истории. - Новосибирск : Наука, Сибирское отделение, 1985. - 203 с.",
      "page": 32,
      "chapter": "Глава I. Морфологическое описание деепричастий якутского языка",
      "topic": "Первичные деепричастия. 2. Деепричастие на -а/-ын",
      "section": 23,
      "notes": "Деепричастия на -а/-ны в якутском языке могут употребляться и в парном виде, т.е. могут сочетаться деепричастные формы от основ разных глаголов. Чаще сочетаются основы, близкие по своему значению, которыми выражается единое понятие.",
      "sah": "Кулуба үөҕэ-мөҕө, кирбиитии турбута.",
      "ru": "Голова стоял понося-ругая, наступая (на него).",
      "id": 3,
      "parses": [
         {"pos": 1, "text": "Кулуба", "type": "title", "fst": "ymv", "root": "кулуба", "affixes": ["+N"]},
         {"pos": 2, "text": "үөҕэ", "type": "lowercase", "fst": "ymv", "root": "үөх", "affixes": ["+V", "+CONV#2"]},
         {"pos": 3, "text": "-", "type": "hyphen", "fst": "ymv"},
         {"pos": 4, "text": "мөҕө", "type": "lowercase", "fst": "ymv", "root": "мөх", "affixes": ["+V", "+CONV#2"]},
         {"pos": 5, "text": ",", "type": "comma", "fst": "ymv"},
         {"pos": 6, "text": "кирбиитии", "type": "lowercase", "fst": "ymv", "root": "кирбиитээ", "affixes": ["+V", "+CONV#2"]},
         {"pos": 7, "text": "турбута", "type": "lowercase", "fst": "ymv", "root": "тур", "affixes": ["+V", "+PART_PAST", "+POSS.3SG"]},
         {"pos": 8, "text": ".", "type": "period", "fst": "ymv"}
      ]
   },
   {
      "source": "Коркина, Евдокия Иннокентьевна. Деепричастия в якутском языке / Е. И. Коркина; отв. ред. к. филол. н. Н. Е. Петров; Акад. наук СССР, Сиб. отд-ние, Якут. фил., Ин-т яз., лит. и истории. - Новосибирск : Наука, Сибирское отделение, 1985. - 203 с.",
      "page": 32,
      "chapter": "Глава I. Морфологическое описание деепричастий якутского языка",
      "topic": "Первичные деепричастия. 2. Деепричастие на -а/-ын",
      "section": 23,
      "notes": "Деепричастия на -а/-ны в якутском языке могут употребляться и в парном виде, т.е. могут сочетаться деепричастные формы от основ разных глаголов. Чаще сочетаются основы, близкие по своему значению, которыми выражается единое понятие.",
      "sah": "Аҕалара Прокопий идэтинэн ыраах тыаҕа бултуу-алтыы тахсыбыта.",
      "ru": "Их отец Прокопий по привычке уехал далеко в лес охотиться?",
      "id": 4,
      "parses": [
         {"pos": 1, "text": "Аҕалара", "type": "title", "fst": "ymv", "root": "аҕа", "affixes": ["+N", "+PL", "+POSS.3SG"]},
         {"pos": 2, "text": "Прокопий", "type": "title", "fst": "yma", "root": "прокопи", "affixes": ["+N", "+VRBLZ#2"]},
         {"pos": 3, "text": "идэтинэн", "type": "lowercase", "fst": "ymv", "root": "идэ", "affixes": ["+N", "+POSS.3SG", "+INST"]},
         {"pos": 4, "text": "ыраах", "type": "lowercase", "fst": "ymv", "root": "ыраах", "affixes": ["+Adj"]},
         {"pos": 5, "text": "тыаҕа", "type": "lowercase", "fst": "ymv", "root": "тыа", "affixes": ["+N", "+DAT"]},
         {"pos": 6, "text": "бултуу", "type": "lowercase", "fst": "ymv", "root": "булт", "affixes": ["+N", "+VRBLZ#1", "+CONV#2"]},
         {"pos": 7, "text": "-", "type": "hyphen", "fst": "ymv"},
         {"pos": 8, "text": "алтыы", "type": "lowercase", "fst": "yma", "root": "алтаа", "affixes": ["+V", "+CONV#2"]},
         {"pos": 9, "text": "тахсыбыта", "type": "lowercase", "fst": "ymv", "root": "таҕыс", "affixes": ["+V", "+PART_PAST", "+POSS.3SG"]},
         {"pos": 10, "text": ".", "type": "period", "fst": "ymv"}
      ]
   },
   {
      "source": "Коркина, Евдокия Иннокентьевна. Деепричастия в якутском языке / Е. И. Коркина; отв. ред. к. филол. н. Н. Е. Петров; Акад. наук СССР, Сиб. отд-ние, Якут. фил., Ин-т яз., лит. и истории. - Новосибирск : Наука, Сибирское отделение, 1985. - 203 с.",
      "page": 32,
      "chapter": "Глава I. Морфологическое описание деепричастий якутского языка",
      "topic": "Первичные деепричастия. 2. Деепричастие на -а/-ын",
      "section": 23,
      "notes": "Могут сочетаться и антонимичные основы; в этом случае передается чередование, следование действий друг за другом.",
      "sah": "Пассажирдар киирэ-тахса, биир кэм төттөрү-таары аалыҥнаһа сылдьаллар.",
      "ru": "Пассажиры входят заходят, Bсe толкаются взад-вперед.",
      "id": 6,
      "parses": [
         {"pos": 1, "text": "Пассажирдар", "type": "title", "fst": "ymv", "root": "пассажир", "affixes": ["+N", "+PL"]},
         {"pos": 2, "text": "киирэ", "type": "lowercase", "fst": "ymv", "root": "киир", "affixes": ["+V", "+CONV#2"]},
         {"pos": 3, "text": "-", "type": "hyphen", "fst": "ymv"},
         {"pos": 4, "text": "тахса", "type": "lowercase", "fst": "ymv", "root": "таҕыс", "affixes": ["+V", "+CONV#2"]},
         {"pos": 5, "text": ",", "type": "comma", "fst": "ymv"},
         {"pos": 6, "text": "биир", "type": "lowercase", "fst": "ymv", "root": "биир", "affixes": ["+Num"]},
         {"pos": 7, "text": "кэм", "type": "lowercase", "fst": "ymv", "root": "кэм", "affixes": ["+N"]},
         {"pos": 8, "text": "төттөрү", "type": "lowercase", "fst": "ymv", "root": "төнүн", "affixes": ["+V", "+CSTV", "+ADVZ#1"]},
         {"pos": 9, "text": "-", "type": "hyphen", "fst": "ymv"},
         {"pos": 10, "text": "таары", "type": "lowercase", "fst": "ymv", "root": "таары", "affixes": ["+Adv"]},
         {"pos": 11, "text": "аалыҥнаһа", "type": "lowercase", "fst": "ymv", "root": "аалыҥнаа", "affixes": ["+V", "+RECP", "+CONV#2"]},
         {"pos": 12, "text": "сылдьаллар", "type": "lowercase", "fst": "ymv", "root": "сырыт", "affixes": ["+V", "+PART_PRES", "+PL"]},
         {"pos": 13, "text": ".", "type": "period", "fst": "ymv"}
      ]
   },
   {
      "source": "Коркина, Евдокия Иннокентьевна. Деепричастия в якутском языке / Е. И. Коркина; отв. ред. к. филол. н. Н. Е. Петров; Акад. наук СССР, Сиб. отд-ние, Якут. фил., Ин-т яз., лит. и истории. - Новосибирск : Наука, Сибирское отделение, 1985. - 203 с.",
      "page": 32,
      "chapter": "Глава I. Морфологическое описание деепричастий якутского языка",
      "topic": "Первичные деепричастия. 2. Деепричастие на -а/-ын",
      "section": 23,
      "notes": "Могут сочетаться и антонимичные основы; в этом случае передается чередование, следование действий друг за другом.",
      "sah": "Ити кэргэн мэлдьи этиһэ-иллэһэ олорор.",
      "ru": "Эта семья живет, вечно ссорясь мирясь.",
      "id": 7,
      "parses": [
         {"pos": 1, "text": "Ити", "type": "title", "fst": "fst", "root": "ити", "affixes": ["+Pron"]},
         {"pos": 2, "text": "кэргэн", "type": "lowercase", "fst": "fst", "root": "кэргэн", "affixes": ["+N"]},
         {"pos": 3, "text": "мэлдьи", "type": "lowercase", "fst": "fst", "root": "мэлдьи", "affixes": ["+Adv"]},
         {"pos": 4, "text": "этиһэ", "type": "lowercase", "fst": "fst", "root": "этис", "affixes": ["+V", "+CONV#2"]},
         {"pos": 5, "text": "-", "type": "hyphen", "fst": "fst"},
         {"pos": 6, "text": "иллэһэ", "type": "lowercase", "fst": "fst", "root": "иллэс", "affixes": ["+V", "+CONV#2"]},
         {"pos": 7, "text": "олорор", "type": "lowercase", "fst": "fst", "root": "олор", "affixes": ["+V", "+PART_PRES"]},
         {"pos": 8, "text": ".", "type": "period", "fst": "fst"}
      ]
   }
]