[
   {
      "source": "Петров, Николай Егорович. Частицы в якутском языке. - Якутск : Кн.изд-во, 1978. - 298 с.",
      "page": 182,
      "chapter": "Глава 2. Собственно частицы",
      "topic": "Частица этээ",
      "section": 51,
      "notes": "Во-вторых, частица этээ имеет усилительно-утвердительное значение.",
      "sah": "Коля хайаан да кыайыа этээ.",
      "ru": "Коля непременно победил бы.",
      "id": 10,
      "parses": [
         {"pos": 1, "text": "Коля", "type": "title", "fst": "fst"},
         {"pos": 2, "text": "хайаан", "type": "lowercase", "fst": "fst", "root": "хайаа", "affixes": ["+V", "+CONV#1"]},
         {"pos": 2, "text": "хайаан", "type": "lowercase", "fst": "fst", "root": "хайа", "affixes": ["+Pron", "+INST"]},
         {"pos": 2, "text": "хайаан", "type": "lowercase", "fst": "fst", "root": "хай", "affixes": ["+V", "+CONV#1"]},
         {"pos": 3, "text": "да", "type": "lowercase", "fst": "fst", "root": "да", "affixes": ["+Part"]},
         {"pos": 4, "text": "кыайыа", "type": "lowercase", "fst": "fst", "root": "кыай", "affixes": ["+V", "+PART_FUT"]},
         {"pos": 4, "text": "кыайыа", "type": "lowercase", "fst": "fst", "root": "кыа", "affixes": ["+N", "+VRBLZ#2", "+PART_FUT"]},
         {"pos": 5, "text": "этээ", "type": "lowercase", "fst": "fst", "root": "этээ", "affixes": ["+Part"]},
         {"pos": 5, "text": "этээ", "type": "lowercase", "fst": "fst", "root": "эт", "affixes": ["+N", "+VRBLZ#3"]},
         {"pos": 6, "text": ".", "type": "period", "fst": "fst"}
      ]
   },
   {
      "source": "Петров, Николай Егорович. Частицы в якутском языке. - Якутск : Кн.изд-во, 1978. - 298 с.",
      "page": 182,
      "chapter": "Глава 2. Собственно частицы",
      "topic": "Частица этээ",
      "section": 51,
      "notes": "Кроме указанной частицы, есть ее омоним по происхождению, синоним по значению - частица этээ, образованная путем слияния этэ с частицей ээ (этэ+ээ этээ). Она отличается от первой едва уловимым рисунком произношения (несколько пониженная интонация) и употребляется только в утвердительном значении с оттенком скрытого осуждения, иронии, обиды. Таким образом, лексема этээ представляет собою две частицы, синонимичных по своему значению.",
      "sah": "Билигин улахан саҕа буолбутун иһин, син биир алааска буорга-сыыска булкуллан улааппыппыт этээ.",
      "ru": "Хотя он и задается сейчас, мы ведь, как-никак, выросли с ним в одном аласе в одинаковых сельских условиях.",
      "id": 14,
      "parses": [
         {"pos": 1, "text": "Билигин", "type": "title", "fst": "fst", "root": "билигин", "affixes": ["+Adv"]},
         {"pos": 1, "text": "Билигин", "type": "title", "fst": "fst", "root": "бил", "affixes": ["+V", "+NMLZ#5", "+POSS.3SG", "+ACC"]},
         {"pos": 2, "text": "улахан", "type": "lowercase", "fst": "fst", "root": "улахан", "affixes": ["+Adj"]},
         {"pos": 3, "text": "саҕа", "type": "lowercase", "fst": "fst", "root": "сах", "affixes": ["+N", "+POSS.3SG"]},
         {"pos": 3, "text": "саҕа", "type": "lowercase", "fst": "fst", "root": "сах", "affixes": ["+V", "+CONV#2"]},
         {"pos": 3, "text": "саҕа", "type": "lowercase", "fst": "fst", "root": "саҕа", "affixes": ["+N"]},
         {"pos": 3, "text": "саҕа", "type": "lowercase", "fst": "fst", "root": "саҕа", "affixes": ["+POST"]},
         {"pos": 3, "text": "саҕа", "type": "lowercase", "fst": "fst", "root": "сай", "affixes": ["+V", "+NMLZ#6", "+POSS.3SG"]},
         {"pos": 4, "text": "буолбутун", "type": "lowercase", "fst": "fst", "root": "буол", "affixes": ["+V", "+PART_PAST", "+POSS.3SG", "+ACC"]},
         {"pos": 5, "text": "иһин", "type": "lowercase", "fst": "fst", "root": "ис", "affixes": ["+N", "+POSS.3SG", "+ACC"]},
         {"pos": 5, "text": "иһин", "type": "lowercase", "fst": "fst", "root": "ис", "affixes": ["+V", "+REFL"]},
         {"pos": 5, "text": "иһин", "type": "lowercase", "fst": "fst", "root": "иһин", "affixes": ["+POST"]},
         {"pos": 6, "text": ",", "type": "comma", "fst": "fst"},
         {"pos": 7, "text": "син", "type": "lowercase", "fst": "fst", "root": "син", "affixes": ["+Adv"]},
         {"pos": 8, "text": "биир", "type": "lowercase", "fst": "fst", "root": "биир", "affixes": ["+Num"]},
         {"pos": 8, "text": "биир", "type": "lowercase", "fst": "fst", "root": "бии", "affixes": ["+N", "+VRBLZ#4"]},
         {"pos": 9, "text": "алааска", "type": "lowercase", "fst": "fst", "root": "алаас", "affixes": ["+N", "+DAT"]},
         {"pos": 9, "text": "алааска", "type": "lowercase", "fst": "fst", "root": "алаас", "affixes": ["+N", "+DIM#3"]},
         {"pos": 10, "text": "буорга", "type": "lowercase", "fst": "fst", "root": "буор", "affixes": ["+N", "+DAT"]},
         {"pos": 11, "text": "-", "type": "hyphen", "fst": "fst"},
         {"pos": 12, "text": "сыыска", "type": "lowercase", "fst": "fst", "root": "сыыс", "affixes": ["+N", "+DAT"]},
         {"pos": 12, "text": "сыыска", "type": "lowercase", "fst": "fst", "root": "сыыс", "affixes": ["+N", "+DIM#3"]},
         {"pos": 13, "text": "булкуллан", "type": "lowercase", "fst": "fst", "root": "булкуй", "affixes": ["+V", "+PASS", "+CONV#1"]},
         {"pos": 14, "text": "улааппыппыт", "type": "lowercase", "fst": "fst", "root": "улаат", "affixes": ["+V", "+PART_PAST", "+POSS.1PL"]},
         {"pos": 14, "text": "улааппыппыт", "type": "lowercase", "fst": "fst", "root": "улаат", "affixes": ["+V", "+PART_PAST", "+1PL"]},
         {"pos": 15, "text": "этээ", "type": "lowercase", "fst": "fst", "root": "этээ", "affixes": ["+Part"]},
         {"pos": 15, "text": "этээ", "type": "lowercase", "fst": "fst", "root": "эт", "affixes": ["+N", "+VRBLZ#3"]},
         {"pos": 16, "text": ".", "type": "period", "fst": "fst"}
      ]
   }
]